boterham/__init__.py
boterham/cli.py
boterham/helpers.py
boterham/loader.py
boterham/postprocess.py
boterham/preprocess.py
boterham/property_logic.py
boterham/terrain.py
boterham/version.py
panda3d_boterham-0.33.dist-info/METADATA
panda3d_boterham-0.33.dist-info/WHEEL
panda3d_boterham-0.33.dist-info/entry_points.txt
panda3d_boterham-0.33.dist-info/top_level.txt
panda3d_boterham-0.33.dist-info/RECORD
