Metadata-Version: 2.1
Name: panda3d-boterham
Version: 0.33
Summary: Pre-and-post-processor for blend2bam, a tool to convert Blender blend files to Panda3D BAM files
Home-page: https://github.com/TheCheapestPixels/panda3d-boterham
Author: jan Entikan
License: MIT
Keywords: panda3d gamedev
Platform: UNKNOWN
Classifier: Development Status :: 4 - Beta
Classifier: License :: OSI Approved :: MIT License
Classifier: Programming Language :: Python
Classifier: Programming Language :: Python :: 3
Classifier: Programming Language :: Python :: 3.6
Classifier: Programming Language :: Python :: 3.7
Classifier: Programming Language :: Python :: 3.8
Requires-Dist: panda3d
Requires-Dist: panda3d-gltf
Requires-Dist: panda3d-blend2bam
